ou_tm129_py/__init__.py
ou_tm129_py-0.0.9.dist-info/LICENSE
ou_tm129_py-0.0.9.dist-info/METADATA
ou_tm129_py-0.0.9.dist-info/WHEEL
ou_tm129_py-0.0.9.dist-info/top_level.txt
ou_tm129_py-0.0.9.dist-info/RECORD
