Metadata-Version: 2.1
Name: ou-tm129-py
Version: 0.0.9
Summary: Python environment for TM129
Home-page: https://github.com/innovationOUtside/ou-tm129-py
Author: Tony Hirst
Author-email: tony.hirst@open.ac.uk
License: MIT License
Platform: UNKNOWN
Classifier: Development Status :: 3 - Alpha
Classifier: Environment :: Web Environment
Classifier: Intended Audience :: Education
Classifier: License :: Free For Educational Use
Classifier: Programming Language :: Python :: 3.6
Classifier: Programming Language :: Python :: 3.7
Classifier: Topic :: Education
Classifier: Topic :: Scientific/Engineering :: Visualization
License-File: LICENSE
Requires-Dist: myst-nb
Requires-Dist: jupytext
Requires-Dist: jupyter-server-proxy
Requires-Dist: nbzip
Requires-Dist: nbresuse
Requires-Dist: nbgitpuller
Requires-Dist: tqdm
Requires-Dist: jupyter-contrib-nbextensions
Requires-Dist: jupyter-wysiwyg
Requires-Dist: jupyterthemes
Requires-Dist: nbtutor
Requires-Dist: RISE
Requires-Dist: nb-extension-tagstyler
Requires-Dist: nb-extension-empinken
Requires-Dist: nb-cell-execution-status
Requires-Dist: ipywidgets (>=7.5.0)
Requires-Dist: nbconvert (>=5.5.0)
Requires-Dist: drawSvg
Requires-Dist: blockdiag
Requires-Dist: blockdiagMagic
Requires-Dist: noisify
Requires-Dist: flake8
Requires-Dist: pycodestyle
Requires-Dist: pycodestyle-magic
Requires-Dist: autopep8
Requires-Dist: pep8-naming
Requires-Dist: flake8-bugbear
Requires-Dist: flake8-docstrings
Requires-Dist: flake8-builtins
Requires-Dist: pandas-vet
Requires-Dist: numpy
Requires-Dist: pandas
Requires-Dist: matplotlib
Requires-Dist: plotly
Requires-Dist: seaborn
Requires-Dist: cufflinks
Requires-Dist: durable-rules
Requires-Dist: nbev3devsim (>=0.0.9)
Requires-Dist: sklearn
Requires-Dist: palettable
Provides-Extra: al
Provides-Extra: production
